{
    "name" : "core_epilogue",
    "title" : "Epilogue",
    "icon" : "black_gem",
    "prerequisite": "core_amber_noon",
    "missions" : [
        {
            "name" : "grim_reminder",
            "title" : "A Grim reminder",
            "map" : "core_epilogue_grim_reminder.tofmap.json",
            "description" : "As the people of Amber Noon celebrate the defeat of Obsidian Night, Warlord Grim finds himself imprisoned and awaiting trial. At least until some unexpected visitors barge in...",
            "marker" : [520, 20],
            "players": [
                {
                    "side" : "black",
                    "ap" : 50,
                    "type" : "human"
                },
                {
                    "side" : "yellow",
                    "ap" : 0,
                    "type" : "ai"
                }
            ]
        }
    ]
}
